CHANGES
COPYING
INSTALL
README
setup.py
bin/kforge-install
bin/kforgeinstall-test
src/kforgeinstall/__init__.py
src/kforgeinstall/cli.py
src/kforgeinstall/clitest.py
src/kforgeinstall/test.py
src/kforgeinstall.egg-info/PKG-INFO
src/kforgeinstall.egg-info/SOURCES.txt
src/kforgeinstall.egg-info/dependency_links.txt
src/kforgeinstall.egg-info/not-zip-safe
src/kforgeinstall.egg-info/requires.txt
src/kforgeinstall.egg-info/top_level.txt