Metadata-Version: 1.0
Name: kforgeinstall
Version: 0.9
Summary: Installer for KForge software.
Home-page: UNKNOWN
Author: Appropriate Software Foundation
Author-email: john.bywater@appropriatesoftware.net
License: AGPL
Platform: UNKNOWN
